tinytorchtest/__init__.py
tinytorchtest/_version.py
tinytorchtest/tinytorchtest.py
tinytorchtest-1.2.3.dist-info/LICENSE
tinytorchtest-1.2.3.dist-info/METADATA
tinytorchtest-1.2.3.dist-info/WHEEL
tinytorchtest-1.2.3.dist-info/RECORD
