Metadata-Version: 2.1
Name: tinytorchtest
Version: 1.2.3
Summary: A tiny test suite for pytorch based machine learning models.
Home-page: https://github.com/abdrysdale/tinytorchtest
License: GPL-3.0-or-later
Author: Alex
Author-email: adrysdale@protonmail.com
Requires-Python: >=3.8,<4.0
Classifier: License :: OSI Approved :: GNU General Public License v3 or later (GPLv3+)
Classifier: Programming Language :: Python :: 3
Classifier: Programming Language :: Python :: 3.8
Classifier: Programming Language :: Python :: 3.9
Classifier: Programming Language :: Python :: 3.10
Classifier: Programming Language :: Python :: 3.11
Classifier: Programming Language :: Python :: 3.12
Requires-Dist: toml (>=0.10.2,<0.11.0)
Requires-Dist: torch (>=1.11)
Project-URL: Repository, https://github.com/abdrysdale/tinytorchtest
